deepecohab/__init__.py
deepecohab/version.py
deepecohab/antenna_analysis/__init__.py
deepecohab/antenna_analysis/activity.py
deepecohab/antenna_analysis/chasings.py
deepecohab/antenna_analysis/incohort_sociability.py
deepecohab/core/__init__.py
deepecohab/core/create_data_structure.py
deepecohab/core/create_project.py
deepecohab/dash/dash_layouts.py
deepecohab/dash/dash_plotting.py
deepecohab/dash/dashboard.py
deepecohab/dash/plot_factory.py
deepecohab/dash/assets/style.css
deepecohab/utils/__init___.py
deepecohab/utils/auxfun.py
deepecohab/utils/auxfun_dashboard.py
deepecohab/utils/auxfun_plots.py
deepecohab/utils/config_templates.py
deepecohab-0.4.2.3.dist-info/licenses/LICENSE
deepecohab-0.4.2.3.dist-info/METADATA
deepecohab-0.4.2.3.dist-info/WHEEL
deepecohab-0.4.2.3.dist-info/top_level.txt
deepecohab-0.4.2.3.dist-info/RECORD
