Metadata-Version: 2.4
Name: deepecohab
Version: 0.4.2.3
Summary: EcoHab with some machine learning
Author-email: Konrad Danielewski <k.danielewski@nencki.edu.pl>, Ula Włodkowska <u.wlodkowska@nencki.edu.pl>
License-Expression: MIT
Project-URL: Homepage, https://github.com/KonradDanielewski/DeepEcoHab
Project-URL: Issues, https://github.com/KonradDanielewski/DeepEcoHab/issues
Keywords: neuroscience,ecology,dash,data-visualization,data-analysis
Classifier: Programming Language :: Python :: 3
Classifier: Operating System :: OS Independent
Classifier: Intended Audience :: Science/Research
Classifier: Topic :: Scientific/Engineering :: Bio-Informatics
Classifier: Topic :: Scientific/Engineering :: Visualization
Requires-Python: >=3.10
License-File: LICENSE
Requires-Dist: dash
Requires-Dist: dash-bootstrap-components
Requires-Dist: ipykernel
Requires-Dist: kaleido
Requires-Dist: nbformat
Requires-Dist: networkx
Requires-Dist: numpy
Requires-Dist: openskill
Requires-Dist: plotly
Requires-Dist: polars
Requires-Dist: scipy
Requires-Dist: toml
Requires-Dist: tzlocal
Dynamic: license-file
